{
    "times": [
        0.0,
        1.25,
        2.5,
        3.75,
        5.0
    ],
    "aadd21b3": {
        "inverse temperature": 0.1,
        "interaction strengths": [
            0.0005,
            0.001,
            0.0001
        ],
        "delta t's": [
            1.3333333333333333,
            0.6666666666666666,
            5.0
        ],
        "interaction lambda's": [
            0.75,
            1.5,
            0.2
        ],
        "00005": {
            "lindbladian": [],
            "interaction": [
                1.0,
                1.0,
                0.5117505,
                0.4064635,
                0.38418450000000004
            ]
        },
        "0001": {
            "lindbladian": [],
            "interaction": [
                1.0,
                0.4570655,
                0.37920050000000005,
                0.3770175,
                0.3768655
            ]
        },
        "00001": {
            "lindbladian": [],
            "interaction": [
                1.0,
                1.0,
                1.0,
                1.0,
                0.9901840000000001
            ]
        }
    },
    "e038e0fc": {
        "inverse temperature": 0.5,
        "interaction strengths": [
            0.0005,
            0.001,
            0.0001
        ],
        "delta t's": [
            1.3333333333333333,
            0.6666666666666666,
            5.0
        ],
        "interaction lambda's": [
            0.75,
            1.5,
            0.2
        ],
        "00005": {
            "lindbladian": [],
            "interaction": [
                1.0,
                1.0,
                0.585694,
                0.47015850000000003,
                0.4351515
            ]
        },
        "0001": {
            "lindbladian": [],
            "interaction": [
                1.0,
                0.53432,
                0.4264645,
                0.4197345,
                0.4191665
            ]
        },
        "00001": {
            "lindbladian": [],
            "interaction": [
                1.0,
                1.0,
                1.0,
                1.0,
                0.990794
            ]
        }
    },
    "ec0ee8e2": {
        "inverse temperature": 1,
        "interaction strengths": [
            0.0005,
            0.001,
            0.0001
        ],
        "delta t's": [
            1.3333333333333333,
            0.6666666666666666,
            5.0
        ],
        "interaction lambda's": [
            0.75,
            1.5,
            0.2
        ],
        "00005": {
            "lindbladian": [],
            "interaction": [
                1.0,
                1.0,
                0.6873130000000001,
                0.5838895,
                0.5461544999999999
            ]
        },
        "0001": {
            "lindbladian": [],
            "interaction": [
                1.0,
                0.6459725000000001,
                0.5373535,
                0.528973,
                0.5282325
            ]
        },
        "00001": {
            "lindbladian": [],
            "interaction": [
                1.0,
                1.0,
                1.0,
                1.0,
                0.991462
            ]
        }
    },
    "8394f615": {
        "inverse temperature": 5,
        "interaction strengths": [
            0.0005,
            0.001,
            0.0001
        ],
        "delta t's": [
            1.3333333333333333,
            0.6666666666666666,
            5.0
        ],
        "interaction lambda's": [
            0.75,
            1.5,
            0.2
        ],
        "00005": {
            "lindbladian": [],
            "interaction": [
                1.0,
                1.0,
                0.9849169999999999,
                0.984296,
                0.9830895
            ]
        },
        "0001": {
            "lindbladian": [],
            "interaction": [
                1.0,
                0.9885079999999999,
                0.984128,
                0.9841890000000001,
                0.9842650000000001
            ]
        },
        "00001": {
            "lindbladian": [],
            "interaction": [
                1.0,
                1.0,
                1.0,
                1.0,
                0.9930265
            ]
        }
    },
    "1dac6af5": {
        "inverse temperature": 10,
        "interaction strengths": [
            0.0005,
            0.001,
            0.0001
        ],
        "delta t's": [
            1.3333333333333333,
            0.6666666666666666,
            5.0
        ],
        "interaction lambda's": [
            0.75,
            1.5,
            0.2
        ],
        "00005": {
            "lindbladian": [],
            "interaction": [
                1.0,
                1.0,
                0.992858,
                0.9955405000000002,
                0.995792
            ]
        },
        "0001": {
            "lindbladian": [],
            "interaction": [
                1.0,
                0.997809,
                0.9970755000000001,
                0.9974780000000001,
                0.9975904999999999
            ]
        },
        "00001": {
            "lindbladian": [],
            "interaction": [
                1.0,
                1.0,
                1.0,
                1.0,
                0.9930655
            ]
        }
    }
}